league_of_legends_decoded_replay_packets_gym/__init__.py
league_of_legends_decoded_replay_packets_gym/cli.py
league_of_legends_decoded_replay_packets_gym/diff_system.py
league_of_legends_decoded_replay_packets_gym/interpolation.py
league_of_legends_decoded_replay_packets_gym/league_replays_gym.py
league_of_legends_decoded_replay_packets_gym/observation_utils.py
league_of_legends_decoded_replay_packets_gym/observations.py
league_of_legends_decoded_replay_packets_gym/packets.py
league_of_legends_decoded_replay_packets_gym/types.py
league_of_legends_decoded_replay_packets_gym-0.1.2.dist-info/licenses/LICENSE
league_of_legends_decoded_replay_packets_gym-0.1.2.dist-info/METADATA
league_of_legends_decoded_replay_packets_gym-0.1.2.dist-info/WHEEL
league_of_legends_decoded_replay_packets_gym-0.1.2.dist-info/entry_points.txt
league_of_legends_decoded_replay_packets_gym-0.1.2.dist-info/top_level.txt
league_of_legends_decoded_replay_packets_gym-0.1.2.dist-info/RECORD
