Metadata-Version: 2.4
Name: league-of-legends-decoded-replay-packets-gym
Version: 0.1.2
Summary: A Gymnasium environment for League of Legends decoded replay packets, enabling esports research, AI development, and gameplay analysis.
Author-email: League Parser Team <parser@league.com>
License:                                  Apache License
Project-URL: Homepage, https://github.com/Maknee/league-of-legends-decoded-replay-packets-gym
Project-URL: Documentation, https://github.com/Maknee/league-of-legends-decoded-replay-packets-gym/blob/main/README.md
Project-URL: Repository, https://github.com/Maknee/league-of-legends-decoded-replay-packets-gym
Project-URL: Bug Tracker, https://github.com/Maknee/league-of-legends-decoded-replay-packets-gym/issues
Keywords: league-of-legends,esports,ai,reinforcement-learning,gymnasium,replay-analysis,gaming,neural-networks
Classifier: Development Status :: 4 - Beta
Classifier: Intended Audience :: Developers
Classifier: Intended Audience :: Science/Research
Classifier: License :: OSI Approved :: MIT License
Classifier: Programming Language :: Python :: 3
Classifier: Programming Language :: Python :: 3.8
Classifier: Programming Language :: Python :: 3.9
Classifier: Programming Language :: Python :: 3.10
Classifier: Programming Language :: Python :: 3.11
Classifier: Topic :: Games/Entertainment
Classifier: Topic :: Scientific/Engineering :: Artificial Intelligence
Requires-Python: >=3.8
License-File: LICENSE
Requires-Dist: gymnasium>=0.26.0
Requires-Dist: numpy>=1.21.0
Requires-Dist: datasets>=2.0.0
Requires-Dist: huggingface-hub>=0.10.0
Requires-Dist: tqdm>=4.64.0
Requires-Dist: pydantic>=1.8.0
Provides-Extra: ai
Requires-Dist: torch>=1.12.0; extra == "ai"
Requires-Dist: torchvision>=0.13.0; extra == "ai"
Requires-Dist: matplotlib>=3.5.0; extra == "ai"
Requires-Dist: seaborn>=0.11.0; extra == "ai"
Requires-Dist: tensorboard>=2.8.0; extra == "ai"
Requires-Dist: scikit-learn>=1.1.0; extra == "ai"
Provides-Extra: dev
Requires-Dist: pytest>=7.0.0; extra == "dev"
Requires-Dist: pytest-cov>=3.0.0; extra == "dev"
Requires-Dist: black>=22.0.0; extra == "dev"
Requires-Dist: isort>=5.10.0; extra == "dev"
Requires-Dist: flake8>=4.0.0; extra == "dev"
Requires-Dist: mypy>=0.950; extra == "dev"
Requires-Dist: pre-commit>=2.17.0; extra == "dev"
Provides-Extra: viz
Requires-Dist: matplotlib>=3.5.0; extra == "viz"
Requires-Dist: pillow>=9.0.0; extra == "viz"
Requires-Dist: opencv-python>=4.5.0; extra == "viz"
Requires-Dist: imageio>=2.19.0; extra == "viz"
Provides-Extra: all
Requires-Dist: torch>=1.12.0; extra == "all"
Requires-Dist: torchvision>=0.13.0; extra == "all"
Requires-Dist: matplotlib>=3.5.0; extra == "all"
Requires-Dist: seaborn>=0.11.0; extra == "all"
Requires-Dist: tensorboard>=2.8.0; extra == "all"
Requires-Dist: scikit-learn>=1.1.0; extra == "all"
Requires-Dist: pillow>=9.0.0; extra == "all"
Requires-Dist: opencv-python>=4.5.0; extra == "all"
Requires-Dist: imageio>=2.19.0; extra == "all"
Requires-Dist: pytest>=7.0.0; extra == "all"
Requires-Dist: pytest-cov>=3.0.0; extra == "all"
Requires-Dist: black>=22.0.0; extra == "all"
Requires-Dist: isort>=5.10.0; extra == "all"
Requires-Dist: flake8>=4.0.0; extra == "all"
Requires-Dist: mypy>=0.950; extra == "all"
Requires-Dist: pre-commit>=2.17.0; extra == "all"
Dynamic: license-file
